gitlab_release.py
gitlab_release-5.6.dist-info/LICENSE
gitlab_release-5.6.dist-info/METADATA
gitlab_release-5.6.dist-info/WHEEL
gitlab_release-5.6.dist-info/entry_points.txt
gitlab_release-5.6.dist-info/top_level.txt
gitlab_release-5.6.dist-info/RECORD
