Metadata-Version: 2.1
Name: gitlab-release
Version: 5.6
Summary: Utility for use in gitlab ci to upload files (from build) to the current projects release (tag)
Home-page: https://gitlab.com/alelec/gitlab-release
Author: Andrew Leech
Author-email: andrew@alelec.net
License: MIT
Platform: UNKNOWN
License-File: LICENSE
Requires-Dist: requests
